roster/__init__.py
roster/abc.py
roster/concrete.py
roster-0.1.10.dist-info/LICENSE
roster-0.1.10.dist-info/WHEEL
roster-0.1.10.dist-info/METADATA
roster-0.1.10.dist-info/RECORD
