Metadata-Version: 2.1
Name: roster
Version: 0.1.10
Summary: Python object registers. Keep track of your classes, functions and data.
Home-page: https://github.com/tombulled/roster
License: MIT
Keywords: youtube,roster,record,register
Author: Tom Bulled
Author-email: 26026015+tombulled@users.noreply.github.com
Requires-Python: >=3.8,<4.0
Classifier: License :: OSI Approved :: MIT License
Classifier: Programming Language :: Python :: 3
Classifier: Programming Language :: Python :: 3.8
Classifier: Programming Language :: Python :: 3.9
Classifier: Programming Language :: Python :: 3.10
Classifier: Programming Language :: Python :: 3.11
Project-URL: Repository, https://github.com/tombulled/roster
